{
  "parent": "projecte:philosophers_stone",
  "display": {
    "icon": {
      "item": "projecte:klein_star_ein"
    },
    "title": {
      "translate": "advancements.projecte.klein_star"
    },
    "description": {
      "translate": "advancements.projecte.klein_star.description"
    },
    "frame": "task",
    "show_toast": true,
    "announce_to_chat": true,
    "hidden": false
  },
  "criteria": {
    "klein_star": {
      "trigger": "minecraft:inventory_changed",
      "conditions": {
        "items": [
          {
            "item": "projecte:klein_star_ein"
          }
        ]
      }
    }
  },
  "requirements": [
    [
      "klein_star"
    ]
  ]
}