{
  "parent": "minecraft:recipes/root",
  "rewards": {
    "recipes": [
      "projecte:gem_boots"
    ]
  },
  "criteria": {
    "has_boots": {
      "trigger": "minecraft:inventory_changed",
      "conditions": {
        "items": [
          {
            "item": "projecte:rm_boots"
          }
        ]
      }
    },
    "has_the_recipe": {
      "trigger": "minecraft:recipe_unlocked",
      "conditions": {
        "recipe": "projecte:gem_boots"
      }
    }
  },
  "requirements": [
    [
      "has_boots",
      "has_the_recipe"
    ]
  ]
}