{
  "parent": "minecraft:recipes/root",
  "rewards": {
    "recipes": [
      "projecte:red_matter_block"
    ]
  },
  "criteria": {
    "has_red_matter": {
      "trigger": "minecraft:inventory_changed",
      "conditions": {
        "items": [
          {
            "item": "projecte:red_matter"
          }
        ]
      }
    },
    "has_the_recipe": {
      "trigger": "minecraft:recipe_unlocked",
      "conditions": {
        "recipe": "projecte:red_matter_block"
      }
    }
  },
  "requirements": [
    [
      "has_red_matter",
      "has_the_recipe"
    ]
  ]
}